<?xml version="1.0" encoding="UTF-8"?>
<beans xmlns="http://www.springframework.org/schema/beans"
	xmlns:xsi="http://www.w3.org/2001/XMLSchema-instance"
	xmlns:context="http://www.springframework.org/schema/context"
	xmlns:batch="http://www.springframework.org/schema/batch"
	xsi:schemaLocation="
		http://www.springframework.org/schema/beans
		http://www.springframework.org/schema/beans/spring-beans.xsd
		http://www.springframework.org/schema/context
		http://www.springframework.org/schema/context/spring-context.xsd
		http://www.springframework.org/schema/batch
		http://www.springframework.org/schema/batch/spring-batch.xsd
		http://www.springframework.org/schema/jdbc
		http://www.springframework.org/schema/jdbc/spring-jdbc.xsd
	">

	<!-- componentパッケージの設定 -->
	<context:component-scan base-package="jp.co.sysevo" />

	<!-- 設定ファイルの読み込み -->
	<import resource="classpath:/META-INF/spring/job-context.xml"/>

	<!-- Jobリポジトリの設定 -->
	<bean id="jobRepository" class="org.springframework.batch.core.repository.support.MapJobRepositoryFactoryBean">
		<property name="transactionManager" ref="transactionManager"/>
	</bean>

	<!-- Luncherの設定 -->
	<bean id="jobLauncher"
		class="org.springframework.batch.core.launch.support.SimpleJobLauncher">
		<property name="jobRepository" ref="jobRepository" />
	</bean>

	<!-- transactionManager -->
	<bean id="transactionManager" class="org.springframework.jdbc.datasource.DataSourceTransactionManager" lazy-init="true">
		<property name="dataSource" ref="dataSource" />
	</bean>

	<!-- JDBCの設定ファイルのロード -->
	<context:property-placeholder location="classpath:/META-INF/jdbc.properties" />

	<!-- DataSource -->
	<bean id="dataSource" class="org.springframework.jdbc.datasource.DriverManagerDataSource">
		<property name="driverClassName" value="${jdbc.driver.class.name}" />
		<property name="url" value="${jdbc.url}" />
		<property name="username" value="${jdbc.username}" />
		<property name="password" value="${jdbc.password}" />
	</bean>

	<!-- Mybatis -->
	<!-- MapperScannerConfigurer-->
	<bean class="org.mybatis.spring.mapper.MapperScannerConfigurer">
		<property name="basePackage" value="jp.co.sysevo.mapper"/>
	</bean>

</beans>